CHANGES.rst
MANIFEST.in
README.rst
bootstrap.py
buildout.cfg
setup.py
src/zopache/__init__.py
src/zopache.pythonscript.egg-info/PKG-INFO
src/zopache.pythonscript.egg-info/SOURCES.txt
src/zopache.pythonscript.egg-info/dependency_links.txt
src/zopache.pythonscript.egg-info/namespace_packages.txt
src/zopache.pythonscript.egg-info/not-zip-safe
src/zopache.pythonscript.egg-info/requires.txt
src/zopache.pythonscript.egg-info/top_level.txt
src/zopache/pythonscript/__init__.py
src/zopache/pythonscript/interfaces.py
src/zopache/pythonscript/pythonscript.py
src/zopache/pythonscript/browser/__init__.py
src/zopache/pythonscript/browser/pythonscript.py
src/zopache/pythonscript/tests/__init__.py
src/zopache/pythonscript/tests/test_pyscript.py