Metadata-Version: 1.1
Name: zopache.pythonscript
Version: 0.1.0
Summary: content TTW python script function
Home-page: http://pypi.python.org/pypi/zopache.pythonscript
Author: Christopher Lozinski
Author-email: lozinski@freerecruiting.com
License: ZPL 2.1
Platform: UNKNOWN
Classifier: Development Status :: 4 - Beta
Classifier: Intended Audience :: Developers
Classifier: License :: OSI Approved :: Zope Public License
Classifier: Programming Language :: Python
Classifier: Operating System :: OS Independent
Classifier: Topic :: Internet :: WWW/HTTP
Classifier: Topic :: Software Development
Classifier: Framework :: Zope3
